Metadata-Version: 1.1
Name: scelvis
Version: 0.8.8
Summary: Single-cell RNA-seq data visualization
Home-page: https://github.com/bihealth/scelvis
Author: Benedikt Obermayer, Manuel Holtgrewe
Author-email: benedikt.obermayer@bihealth.de, manuel.holtgrewe@bihealth.de
License: MIT license
Keywords: single-cell,visualization,bioinformatics
Platform: UNKNOWN
Classifier: Development Status :: 4 - Beta
Classifier: Intended Audience :: Science/Research
Classifier: License :: OSI Approved :: MIT License
Classifier: Natural Language :: English
Classifier: Programming Language :: Python :: 3
Classifier: Programming Language :: Python :: 3.6
Classifier: Programming Language :: Python :: 3.7
